LICENSE
MANIFEST.in
setup.py
version.py
rask_njord_dhtdb/__init__.py
rask_njord_dhtdb.egg-info/PKG-INFO
rask_njord_dhtdb.egg-info/SOURCES.txt
rask_njord_dhtdb.egg-info/dependency_links.txt
rask_njord_dhtdb.egg-info/requires.txt
rask_njord_dhtdb.egg-info/top_level.txt