Metadata-Version: 1.0
Name: rask-njord-dhtdb
Version: 0.0.7
Summary: Rask DHTDB Client
Home-page: https://gitlab.com/vikingmakt/rask_njord_dhtdb
Author: Umgeher Torgersen
Author-email: me@umgeher.org
License: https://gitlab.com/vikingmakt/rask_njord_dhtdb/raw/master/LICENSE
Platform: UNKNOWN
